equity/__init__.py
equity/equity.py
equity/exceptions.py
equity/model.py
equity/rpc.py
equity/utils.py
equity/cli/__init__.py
equity/cli/__main__.py
equity/cli/compile.py
py_equity-0.1.0.dist-info/LICENSE
py_equity-0.1.0.dist-info/METADATA
py_equity-0.1.0.dist-info/WHEEL
py_equity-0.1.0.dist-info/entry_points.txt
py_equity-0.1.0.dist-info/top_level.txt
py_equity-0.1.0.dist-info/RECORD
