Metadata-Version: 2.1
Name: py-equity
Version: 0.1.0
Summary: Python wrapper around the BUTXO Equity compiler for Bytom protocol.
Home-page: https://github.com/meherett/py-equity
Author: Meheret Tesfaye
Author-email: meherett@zoho.com
License: AGPLv3+
Keywords: eqt
Platform: UNKNOWN
Classifier: Development Status :: 3 - Alpha
Classifier: License :: OSI Approved :: GNU Affero General Public License v3 or later (AGPLv3+)
Classifier: Programming Language :: Python :: 2.7
Classifier: Programming Language :: Python :: 3
Classifier: Programming Language :: Python :: 3.1
Classifier: Programming Language :: Python :: 3.2
Classifier: Programming Language :: Python :: 3.3
Classifier: Programming Language :: Python :: 3.4
Classifier: Programming Language :: Python :: 3.5
Classifier: Programming Language :: Python :: 3.6
Classifier: Programming Language :: Python :: 3.7
Classifier: Programming Language :: Python
Requires-Python: >=2.7,<4
